pikvm_utils.py
PiKVM_utils-1.1.dist-info/LICENSE
PiKVM_utils-1.1.dist-info/METADATA
PiKVM_utils-1.1.dist-info/WHEEL
PiKVM_utils-1.1.dist-info/entry_points.txt
PiKVM_utils-1.1.dist-info/top_level.txt
PiKVM_utils-1.1.dist-info/RECORD
